{
	"song": {
		"player1": "bffurry",
		"player2": "hotheadbored",
		"events": [],
		"notes": [
			{
				"typeOfSection": 0,
				"sectionNotes": [],
				"sectionBeats": 4,
				"altAnim": false,
				"gfSection": false,
				"bpm": 150,
				"changeBPM": false,
				"mustHitSection": false
			},
			{
				"typeOfSection": 0,
				"sectionNotes": [],
				"sectionBeats": 4,
				"altAnim": false,
				"gfSection": false,
				"bpm": 150,
				"changeBPM": false,
				"mustHitSection": false
			},
			{
				"sectionBeats": 4,
				"sectionNotes": [],
				"typeOfSection": 0,
				"gfSection": false,
				"altAnim": false,
				"mustHitSection": false,
				"changeBPM": false,
				"bpm": 110
			},
			{
				"sectionBeats": 4,
				"sectionNotes": [],
				"typeOfSection": 0,
				"gfSection": false,
				"altAnim": false,
				"mustHitSection": false,
				"changeBPM": false,
				"bpm": 110
			},
			{
				"sectionBeats": 4,
				"sectionNotes": [
					[
						9000,
						2,
						0
					],
					[
						9409.09090909091,
						0,
						136.363636363636
					],
					[
						9818.18181818182,
						3,
						136.363636363636
					],
					[
						9545.45454545455,
						1,
						0
					],
					[
						10363.6363636364,
						3,
						0
					],
					[
						10772.7272727273,
						0,
						0
					],
					[
						10636.3636363636,
						3,
						136.363636363636
					]
				],
				"typeOfSection": 0,
				"gfSection": false,
				"altAnim": false,
				"mustHitSection": false,
				"changeBPM": false,
				"bpm": 110
			},
			{
				"sectionBeats": 4,
				"sectionNotes": [
					[
						10909.0909090909,
						1,
						0
					],
					[
						11181.8181818182,
						1,
						0
					],
					[
						11590.9090909091,
						3,
						409.090909090909
					],
					[
						12000,
						1,
						0
					],
					[
						12818.1818181818,
						2,
						136.363636363636
					],
					[
						12545.4545454545,
						0,
						272.727272727273
					]
				],
				"typeOfSection": 0,
				"gfSection": false,
				"altAnim": false,
				"mustHitSection": false,
				"changeBPM": false,
				"bpm": 110
			},
			{
				"typeOfSection": 0,
				"sectionNotes": [
					[
						13363.6363636364,
						3,
						409.090909090909
					],
					[
						13772.7272727273,
						1,
						409.090909090909
					],
					[
						14181.8181818182,
						3,
						409.090909090909
					],
					[
						14727.2727272727,
						1,
						0
					],
					[
						15000,
						0,
						0
					]
				],
				"sectionBeats": 4,
				"altAnim": false,
				"gfSection": false,
				"bpm": 110,
				"changeBPM": false,
				"mustHitSection": false
			},
			{
				"typeOfSection": 0,
				"sectionNotes": [
					[
						15272.7272727273,
						2,
						272.727272727273
					],
					[
						15681.8181818182,
						2,
						272.727272727273
					],
					[
						16090.9090909091,
						2,
						409.090909090909
					],
					[
						16363.6363636364,
						0,
						136.363636363636
					],
					[
						16636.3636363636,
						0,
						272.727272727273
					],
					[
						17181.8181818182,
						0,
						136.363636363636
					],
					[
						16909.0909090909,
						3,
						409.090909090909
					]
				],
				"sectionBeats": 4,
				"altAnim": false,
				"gfSection": false,
				"bpm": 110,
				"changeBPM": false,
				"mustHitSection": false
			},
			{
				"typeOfSection": 0,
				"sectionNotes": [
					[
						17727.2727272727,
						2,
						0
					],
					[
						18136.3636363636,
						0,
						136.363636363636
					],
					[
						18545.4545454545,
						3,
						136.363636363636
					],
					[
						19090.9090909091,
						3,
						0
					],
					[
						19500,
						0,
						0
					],
					[
						19363.6363636364,
						3,
						136.363636363636
					]
				],
				"sectionBeats": 4,
				"altAnim": false,
				"gfSection": false,
				"bpm": 110,
				"changeBPM": false,
				"mustHitSection": true
			},
			{
				"typeOfSection": 0,
				"sectionNotes": [
					[
						19909.0909090909,
						1,
						0
					],
					[
						20318.1818181818,
						3,
						409.090909090909
					],
					[
						21545.4545454545,
						2,
						136.363636363636
					],
					[
						21272.7272727273,
						0,
						272.727272727273
					]
				],
				"sectionBeats": 4,
				"altAnim": false,
				"gfSection": false,
				"bpm": 110,
				"changeBPM": false,
				"mustHitSection": true
			},
			{
				"typeOfSection": 0,
				"sectionNotes": [
					[
						22090.9090909091,
						3,
						409.090909090909
					],
					[
						22500,
						1,
						409.090909090909
					],
					[
						22909.0909090909,
						3,
						409.090909090909
					],
					[
						23454.5454545455,
						1,
						0
					],
					[
						23727.2727272727,
						0,
						0
					]
				],
				"sectionBeats": 4,
				"altAnim": false,
				"gfSection": false,
				"bpm": 110,
				"changeBPM": false,
				"mustHitSection": true
			},
			{
				"typeOfSection": 0,
				"sectionNotes": [
					[
						24000,
						2,
						136.363636363637
					],
					[
						24409.0909090909,
						2,
						136.363636363637
					],
					[
						24818.1818181818,
						2,
						136.363636363636
					],
					[
						25090.9090909091,
						0,
						136.363636363636
					],
					[
						25363.6363636364,
						0,
						136.363636363637
					],
					[
						25636.3636363636,
						3,
						409.090909090909
					]
				],
				"sectionBeats": 4,
				"altAnim": false,
				"gfSection": false,
				"bpm": 110,
				"changeBPM": false,
				"mustHitSection": true
			},
			{
				"typeOfSection": 0,
				"sectionNotes": [
					[
						26454.5454545455,
						1,
						0
					],
					[
						26181.8181818182,
						1,
						136.363636363636
					],
					[
						26863.6363636364,
						2,
						0
					],
					[
						27136.3636363636,
						0,
						136.363636363636
					],
					[
						27272.7272727273,
						3,
						409.090909090909
					],
					[
						27681.8181818182,
						2,
						409.090909090909
					],
					[
						28090.9090909091,
						3,
						0
					]
				],
				"sectionBeats": 4,
				"altAnim": false,
				"gfSection": false,
				"bpm": 110,
				"changeBPM": false,
				"mustHitSection": false
			},
			{
				"typeOfSection": 0,
				"sectionNotes": [
					[
						28636.3636363636,
						2,
						272.727272727273
					],
					[
						29318.1818181818,
						1,
						0
					],
					[
						28909.0909090909,
						1,
						0
					],
					[
						29045.4545454546,
						2,
						272.727272727273
					],
					[
						29454.5454545455,
						0,
						272.727272727273
					],
					[
						29727.2727272727,
						3,
						0
					],
					[
						29863.6363636364,
						1,
						0
					],
					[
						30136.3636363636,
						0,
						0
					],
					[
						30272.7272727273,
						3,
						0
					]
				],
				"sectionBeats": 4,
				"altAnim": false,
				"gfSection": false,
				"bpm": 110,
				"changeBPM": false,
				"mustHitSection": false
			},
			{
				"typeOfSection": 0,
				"sectionNotes": [
					[
						30818.1818181818,
						1,
						272.727272727273
					],
					[
						31090.9090909091,
						0,
						0
					],
					[
						31227.2727272727,
						1,
						272.727272727273
					],
					[
						31500,
						0,
						0
					],
					[
						31636.3636363637,
						2,
						272.727272727273
					],
					[
						31909.0909090909,
						3,
						0
					],
					[
						32045.4545454546,
						1,
						0
					],
					[
						32318.1818181818,
						0,
						0
					],
					[
						32454.5454545455,
						3,
						0
					]
				],
				"sectionBeats": 4,
				"altAnim": false,
				"gfSection": false,
				"bpm": 110,
				"changeBPM": false,
				"mustHitSection": false
			},
			{
				"typeOfSection": 0,
				"sectionNotes": [
					[
						33000,
						0,
						0
					],
					[
						33136.3636363637,
						3,
						0
					],
					[
						33272.7272727273,
						2,
						0
					],
					[
						33409.0909090909,
						0,
						272.727272727273
					],
					[
						33818.1818181818,
						2,
						0
					],
					[
						33681.8181818182,
						3,
						136.363636363636
					],
					[
						34090.9090909091,
						0,
						0
					],
					[
						34227.2727272727,
						1,
						409.090909090909
					],
					[
						34500,
						0,
						0
					],
					[
						34636.3636363637,
						1,
						0
					]
				],
				"sectionBeats": 4,
				"altAnim": false,
				"gfSection": false,
				"bpm": 110,
				"changeBPM": false,
				"mustHitSection": false
			},
			{
				"typeOfSection": 0,
				"sectionNotes": [
					[
						34909.0909090909,
						5,
						136.363636363636
					],
					[
						34909.0909090909,
						1,
						136.363636363636
					],
					[
						35590.9090909091,
						2,
						0
					],
					[
						35863.6363636364,
						0,
						136.363636363636
					],
					[
						36000,
						3,
						272.727272727273
					],
					[
						36409.0909090909,
						2,
						272.727272727273
					],
					[
						35181.8181818182,
						0,
						0
					],
					[
						36818.1818181818,
						0,
						136.363636363636
					]
				],
				"sectionBeats": 4,
				"altAnim": false,
				"gfSection": false,
				"bpm": 110,
				"changeBPM": false,
				"mustHitSection": true
			},
			{
				"typeOfSection": 0,
				"sectionNotes": [
					[
						37363.6363636364,
						2,
						272.727272727273
					],
					[
						37772.7272727273,
						2,
						272.727272727273
					],
					[
						38181.8181818182,
						0,
						272.727272727273
					],
					[
						38590.9090909091,
						1,
						0
					],
					[
						38863.6363636364,
						0,
						0
					],
					[
						39000,
						3,
						0
					]
				],
				"sectionBeats": 4,
				"altAnim": false,
				"gfSection": false,
				"bpm": 110,
				"changeBPM": false,
				"mustHitSection": true
			},
			{
				"typeOfSection": 0,
				"sectionNotes": [
					[
						39545.4545454546,
						1,
						136.363636363637
					],
					[
						39954.5454545455,
						1,
						136.363636363637
					],
					[
						40363.6363636364,
						2,
						136.363636363637
					],
					[
						40636.3636363636,
						3,
						0
					],
					[
						40772.7272727273,
						1,
						0
					],
					[
						41045.4545454546,
						0,
						0
					],
					[
						41181.8181818182,
						3,
						0
					]
				],
				"sectionBeats": 4,
				"altAnim": false,
				"gfSection": false,
				"bpm": 110,
				"changeBPM": false,
				"mustHitSection": true
			},
			{
				"typeOfSection": 0,
				"sectionNotes": [
					[
						41727.2727272727,
						0,
						0
					],
					[
						41863.6363636364,
						3,
						0
					],
					[
						42000,
						2,
						0
					],
					[
						42136.3636363637,
						0,
						272.727272727273
					],
					[
						42545.4545454546,
						2,
						0
					],
					[
						42409.0909090909,
						3,
						136.363636363636
					],
					[
						42818.1818181818,
						0,
						0
					],
					[
						42954.5454545455,
						1,
						409.090909090909
					],
					[
						41454.5454545455,
						4,
						954.545454545454
					],
					[
						42545.4545454546,
						5,
						954.545454545455
					]
				],
				"sectionBeats": 4,
				"altAnim": false,
				"gfSection": false,
				"bpm": 110,
				"changeBPM": false,
				"mustHitSection": true
			},
			{
				"typeOfSection": 0,
				"sectionNotes": [
					[
						43636.3636363637,
						1,
						0
					],
					[
						44045.4545454546,
						1,
						0
					],
					[
						43909.0909090909,
						1,
						0
					],
					[
						44181.8181818182,
						1,
						272.727272727273
					],
					[
						44454.5454545455,
						3,
						272.727272727273
					],
					[
						44727.2727272727,
						2,
						272.727272727273
					],
					[
						45000,
						3,
						272.727272727273
					],
					[
						45272.7272727273,
						1,
						136.363636363636
					],
					[
						45545.4545454546,
						0,
						136.363636363636
					],
					[
						45409.0909090909,
						3,
						0
					]
				],
				"sectionBeats": 4,
				"altAnim": false,
				"gfSection": false,
				"bpm": 110,
				"changeBPM": false,
				"mustHitSection": false
			},
			{
				"typeOfSection": 0,
				"sectionNotes": [
					[
						45818.1818181818,
						3,
						272.727272727273
					],
					[
						46090.9090909091,
						1,
						0
					],
					[
						46363.6363636364,
						3,
						272.727272727273
					],
					[
						46636.3636363637,
						0,
						0
					],
					[
						46909.0909090909,
						2,
						272.727272727273
					],
					[
						47181.8181818182,
						3,
						0
					],
					[
						47454.5454545455,
						0,
						0
					],
					[
						47727.2727272728,
						1,
						0
					]
				],
				"sectionBeats": 4,
				"altAnim": false,
				"gfSection": false,
				"bpm": 110,
				"changeBPM": false,
				"mustHitSection": false
			},
			{
				"typeOfSection": 0,
				"sectionNotes": [
					[
						48818.1818181818,
						3,
						136.363636363637
					],
					[
						49090.9090909091,
						2,
						136.363636363637
					],
					[
						49363.6363636364,
						3,
						136.363636363637
					],
					[
						49636.3636363637,
						1,
						136.363636363637
					],
					[
						49909.0909090909,
						0,
						136.363636363636
					],
					[
						48000,
						0,
						272.727272727273
					],
					[
						48545.4545454546,
						0,
						272.727272727273
					],
					[
						48409.0909090909,
						3,
						0
					]
				],
				"sectionBeats": 4,
				"altAnim": false,
				"gfSection": false,
				"bpm": 110,
				"changeBPM": false,
				"mustHitSection": true
			},
			{
				"typeOfSection": 0,
				"sectionNotes": [
					[
						50181.8181818182,
						3,
						272.727272727273
					],
					[
						50727.2727272727,
						3,
						272.727272727273
					],
					[
						51000,
						0,
						0
					],
					[
						51272.7272727273,
						2,
						136.363636363637
					],
					[
						51545.4545454546,
						3,
						272.727272727273
					],
					[
						50590.9090909091,
						1,
						0
					],
					[
						52090.9090909091,
						3,
						272.727272727273
					]
				],
				"sectionBeats": 4,
				"altAnim": false,
				"gfSection": false,
				"bpm": 110,
				"changeBPM": false,
				"mustHitSection": true
			},
			{
				"typeOfSection": 0,
				"sectionNotes": [
					[
						52363.6363636364,
						1,
						2045.45454545454
					],
					[
						53318.1818181819,
						2,
						1090.90909090909
					],
					[
						52772.7272727273,
						5,
						0
					],
					[
						52636.3636363637,
						5,
						0
					],
					[
						53181.8181818182,
						7,
						272.727272727273
					],
					[
						53454.5454545455,
						6,
						272.727272727273
					],
					[
						53727.2727272727,
						7,
						272.727272727273
					],
					[
						54000,
						5,
						136.363636363636
					],
					[
						54272.7272727273,
						4,
						136.363636363636
					],
					[
						54136.3636363637,
						7,
						0
					],
					[
						52909.0909090909,
						4,
						272.727272727273
					],
					[
						52363.6363636364,
						4,
						272.727272727273
					]
				],
				"sectionBeats": 4,
				"altAnim": false,
				"gfSection": false,
				"bpm": 110,
				"changeBPM": false,
				"mustHitSection": true
			},
			{
				"typeOfSection": 0,
				"sectionNotes": [
					[
						54545.4545454546,
						3,
						272.727272727273
					],
					[
						55090.9090909091,
						3,
						272.727272727273
					],
					[
						55363.6363636364,
						0,
						0
					],
					[
						55636.3636363637,
						2,
						272.727272727273
					],
					[
						55909.0909090909,
						3,
						272.727272727273
					],
					[
						56181.8181818182,
						0,
						0
					],
					[
						54954.5454545455,
						1,
						0
					],
					[
						54545.4545454546,
						3,
						272.727272727273
					],
					[
						54818.1818181818,
						1,
						0
					],
					[
						55090.9090909091,
						3,
						272.727272727273
					],
					[
						55363.6363636364,
						0,
						0
					],
					[
						55636.3636363637,
						2,
						272.727272727273
					],
					[
						55909.0909090909,
						3,
						0
					],
					[
						56181.8181818182,
						0,
						0
					],
					[
						56454.5454545455,
						1,
						0
					],
					[
						55500,
						0,
						0
					],
					[
						56454.5454545455,
						3,
						0
					]
				],
				"sectionBeats": 4,
				"altAnim": false,
				"gfSection": false,
				"bpm": 110,
				"changeBPM": false,
				"mustHitSection": false
			},
			{
				"typeOfSection": 0,
				"sectionNotes": [
					[
						57136.3636363637,
						1,
						0
					],
					[
						57545.4545454546,
						3,
						136.363636363637
					],
					[
						57818.1818181818,
						2,
						272.727272727273
					],
					[
						58363.6363636364,
						1,
						136.363636363637
					],
					[
						58636.3636363637,
						0,
						136.363636363636
					],
					[
						57272.7272727273,
						0,
						272.727272727273
					],
					[
						56727.2727272728,
						0,
						272.727272727273
					],
					[
						58227.2727272728,
						3,
						0
					]
				],
				"sectionBeats": 4,
				"altAnim": false,
				"gfSection": false,
				"bpm": 110,
				"changeBPM": false,
				"mustHitSection": true
			},
			{
				"typeOfSection": 0,
				"sectionNotes": [
					[
						58909.0909090909,
						3,
						272.727272727273
					],
					[
						58909.0909090909,
						0,
						272.727272727273
					],
					[
						59454.5454545455,
						0,
						272.727272727273
					],
					[
						60000,
						2,
						272.727272727273
					],
					[
						60000,
						0,
						272.727272727273
					],
					[
						60545.4545454546,
						0,
						0
					],
					[
						60681.8181818182,
						0,
						0
					],
					[
						60818.1818181819,
						1,
						0
					],
					[
						59863.6363636364,
						3,
						0
					]
				],
				"sectionBeats": 4,
				"altAnim": false,
				"gfSection": false,
				"bpm": 110,
				"changeBPM": false,
				"mustHitSection": true
			},
			{
				"typeOfSection": 0,
				"sectionNotes": [
					[
						61090.9090909091,
						5,
						3681.81818181818
					],
					[
						61090.9090909091,
						7,
						1500
					],
					[
						61363.6363636364,
						0,
						136.363636363636
					],
					[
						61772.7272727273,
						3,
						136.363636363636
					],
					[
						62181.8181818182,
						0,
						136.363636363636
					],
					[
						62727.2727272728,
						0,
						409.090909090909
					],
					[
						63000,
						3,
						136.363636363636
					]
				],
				"sectionBeats": 4,
				"altAnim": false,
				"gfSection": false,
				"bpm": 110,
				"changeBPM": false,
				"mustHitSection": false
			},
			{
				"typeOfSection": 0,
				"sectionNotes": [
					[
						63272.7272727273,
						6,
						1500
					],
					[
						64909.090909091,
						4,
						0
					],
					[
						65181.8181818182,
						7,
						0
					],
					[
						63272.7272727273,
						2,
						0
					],
					[
						63545.4545454546,
						1,
						0
					],
					[
						63681.8181818182,
						2,
						0
					],
					[
						63954.5454545455,
						1,
						0
					],
					[
						64090.9090909091,
						2,
						0
					],
					[
						64363.6363636364,
						1,
						0
					],
					[
						64636.3636363637,
						2,
						0
					],
					[
						64772.7272727273,
						1,
						0
					],
					[
						65045.4545454546,
						3,
						0
					],
					[
						65181.8181818182,
						2,
						0
					],
					[
						65318.1818181819,
						1,
						0
					]
				],
				"sectionBeats": 4,
				"altAnim": false,
				"gfSection": false,
				"bpm": 110,
				"changeBPM": false,
				"mustHitSection": false
			},
			{
				"typeOfSection": 0,
				"sectionNotes": [
					[
						65454.5454545455,
						4,
						3136.36363636364
					],
					[
						65454.5454545455,
						6,
						1500
					],
					[
						67090.9090909091,
						7,
						409.090909090909
					],
					[
						65727.2727272728,
						3,
						272.727272727273
					],
					[
						66000,
						1,
						0
					],
					[
						66136.3636363637,
						3,
						0
					],
					[
						66409.090909091,
						3,
						0
					],
					[
						66545.4545454546,
						0,
						0
					],
					[
						66681.8181818182,
						2,
						0
					],
					[
						66818.1818181819,
						0,
						0
					],
					[
						66954.5454545455,
						1,
						0
					],
					[
						67090.9090909091,
						2,
						0
					],
					[
						67363.6363636364,
						3,
						136.363636363636
					]
				],
				"sectionBeats": 4,
				"altAnim": false,
				"gfSection": false,
				"bpm": 110,
				"changeBPM": false,
				"mustHitSection": false
			},
			{
				"typeOfSection": 0,
				"sectionNotes": [
					[
						67636.3636363637,
						5,
						2045.45454545454
					],
					[
						68727.2727272728,
						7,
						954.545454545455
					],
					[
						67636.3636363637,
						0,
						0
					],
					[
						67909.090909091,
						0,
						0
					],
					[
						68318.1818181819,
						0,
						0
					],
					[
						68045.4545454546,
						0,
						0
					],
					[
						68590.9090909091,
						0,
						0
					],
					[
						68727.2727272728,
						3,
						0
					],
					[
						69000,
						1,
						136.363636363636
					],
					[
						69136.3636363637,
						3,
						0
					],
					[
						69545.4545454546,
						3,
						0
					],
					[
						69409.090909091,
						1,
						136.363636363636
					],
					[
						69681.8181818182,
						0,
						0
					]
				],
				"sectionBeats": 4,
				"altAnim": false,
				"gfSection": false,
				"bpm": 110,
				"changeBPM": false,
				"mustHitSection": false
			},
			{
				"typeOfSection": 0,
				"sectionNotes": [
					[
						69818.1818181819,
						5,
						3681.81818181818
					],
					[
						69818.1818181819,
						7,
						1500
					],
					[
						71454.5454545455,
						4,
						409.090909090909
					],
					[
						70090.9090909091,
						0,
						136.363636363636
					],
					[
						70500,
						3,
						136.363636363636
					],
					[
						70909.0909090909,
						0,
						136.363636363636
					],
					[
						71454.5454545455,
						0,
						409.090909090909
					],
					[
						71727.2727272728,
						3,
						136.363636363636
					]
				],
				"sectionBeats": 4,
				"altAnim": false,
				"gfSection": false,
				"bpm": 110,
				"changeBPM": false,
				"mustHitSection": true
			},
			{
				"typeOfSection": 0,
				"sectionNotes": [
					[
						72000,
						6,
						1500
					],
					[
						73636.3636363637,
						4,
						0
					],
					[
						73909.090909091,
						7,
						0
					],
					[
						72000,
						2,
						0
					],
					[
						72272.7272727273,
						1,
						0
					],
					[
						72409.090909091,
						2,
						0
					],
					[
						72681.8181818182,
						1,
						0
					],
					[
						72818.1818181819,
						2,
						0
					],
					[
						73090.9090909091,
						1,
						0
					],
					[
						73363.6363636364,
						2,
						0
					],
					[
						73500,
						1,
						0
					],
					[
						73772.7272727273,
						3,
						0
					],
					[
						73909.090909091,
						2,
						0
					],
					[
						74045.4545454546,
						1,
						0
					]
				],
				"sectionBeats": 4,
				"altAnim": false,
				"gfSection": false,
				"bpm": 110,
				"changeBPM": false,
				"mustHitSection": true
			},
			{
				"typeOfSection": 0,
				"sectionNotes": [
					[
						74181.8181818182,
						4,
						3136.36363636364
					],
					[
						74181.8181818182,
						6,
						1500
					],
					[
						75818.1818181819,
						7,
						409.090909090909
					],
					[
						74454.5454545455,
						3,
						272.727272727273
					],
					[
						74727.2727272728,
						1,
						0
					],
					[
						74863.6363636364,
						3,
						0
					],
					[
						75136.3636363637,
						3,
						0
					],
					[
						75409.0909090909,
						2,
						0
					],
					[
						75545.4545454546,
						0,
						0
					],
					[
						75681.8181818182,
						1,
						0
					],
					[
						75818.1818181819,
						2,
						0
					],
					[
						76090.9090909091,
						3,
						136.363636363636
					]
				],
				"sectionBeats": 4,
				"altAnim": false,
				"gfSection": false,
				"bpm": 110,
				"changeBPM": false,
				"mustHitSection": true
			},
			{
				"typeOfSection": 0,
				"sectionNotes": [
					[
						76363.6363636364,
						5,
						2045.45454545454
					],
					[
						77454.5454545455,
						7,
						954.545454545455
					],
					[
						76363.6363636364,
						0,
						0
					],
					[
						77045.4545454546,
						0,
						0
					],
					[
						76772.7272727273,
						0,
						0
					],
					[
						77318.1818181819,
						0,
						0
					],
					[
						77454.5454545455,
						3,
						0
					],
					[
						77727.2727272728,
						1,
						136.363636363636
					],
					[
						77863.6363636364,
						3,
						0
					],
					[
						78272.7272727273,
						3,
						0
					],
					[
						78136.3636363637,
						1,
						136.363636363636
					],
					[
						78409.0909090909,
						0,
						0
					]
				],
				"sectionBeats": 4,
				"altAnim": false,
				"gfSection": false,
				"bpm": 110,
				"changeBPM": false,
				"mustHitSection": true
			},
			{
				"typeOfSection": 0,
				"sectionNotes": [],
				"sectionBeats": 4,
				"altAnim": false,
				"gfSection": false,
				"bpm": 110,
				"changeBPM": false,
				"mustHitSection": true
			},
			{
				"typeOfSection": 0,
				"sectionNotes": [],
				"sectionBeats": 4,
				"altAnim": false,
				"gfSection": false,
				"bpm": 110,
				"changeBPM": false,
				"mustHitSection": true
			},
			{
				"typeOfSection": 0,
				"sectionNotes": [],
				"sectionBeats": 4,
				"altAnim": false,
				"gfSection": false,
				"bpm": 110,
				"changeBPM": false,
				"mustHitSection": true
			},
			{
				"typeOfSection": 0,
				"sectionNotes": [],
				"sectionBeats": 4,
				"altAnim": false,
				"gfSection": false,
				"bpm": 110,
				"changeBPM": false,
				"mustHitSection": true
			},
			{
				"typeOfSection": 0,
				"sectionNotes": [
					[
						87545.4545454545,
						2,
						0
					],
					[
						87954.5454545454,
						0,
						136.363636363636
					],
					[
						88363.6363636364,
						3,
						136.363636363636
					],
					[
						88090.9090909091,
						1,
						0
					],
					[
						88909.0909090909,
						3,
						0
					],
					[
						89318.1818181818,
						0,
						0
					],
					[
						89181.8181818182,
						3,
						136.363636363636
					]
				],
				"sectionBeats": 4,
				"altAnim": false,
				"gfSection": false,
				"bpm": 110,
				"changeBPM": false,
				"mustHitSection": false
			},
			{
				"typeOfSection": 0,
				"sectionNotes": [
					[
						89454.5454545454,
						1,
						0
					],
					[
						89727.2727272727,
						1,
						0
					],
					[
						90136.3636363636,
						3,
						409.090909090909
					],
					[
						90545.4545454545,
						1,
						0
					],
					[
						91363.6363636364,
						2,
						136.363636363636
					],
					[
						91090.9090909091,
						0,
						272.727272727273
					]
				],
				"sectionBeats": 4,
				"altAnim": false,
				"gfSection": false,
				"bpm": 110,
				"changeBPM": false,
				"mustHitSection": false
			},
			{
				"typeOfSection": 0,
				"sectionNotes": [
					[
						91909.0909090909,
						3,
						409.090909090909
					],
					[
						92318.1818181818,
						1,
						409.090909090909
					],
					[
						92727.2727272727,
						3,
						409.090909090909
					],
					[
						93272.7272727273,
						1,
						0
					],
					[
						93545.4545454545,
						0,
						0
					]
				],
				"sectionBeats": 4,
				"altAnim": false,
				"gfSection": false,
				"bpm": 110,
				"changeBPM": false,
				"mustHitSection": false
			},
			{
				"typeOfSection": 0,
				"sectionNotes": [
					[
						93818.1818181818,
						2,
						272.727272727273
					],
					[
						94227.2727272727,
						2,
						272.727272727273
					],
					[
						94636.3636363636,
						2,
						409.090909090909
					],
					[
						94909.0909090909,
						0,
						136.363636363636
					],
					[
						95181.8181818182,
						0,
						272.727272727273
					],
					[
						95727.2727272727,
						0,
						136.363636363636
					],
					[
						95454.5454545454,
						3,
						409.090909090909
					]
				],
				"sectionBeats": 4,
				"altAnim": false,
				"gfSection": false,
				"bpm": 110,
				"changeBPM": false,
				"mustHitSection": false
			},
			{
				"typeOfSection": 0,
				"sectionNotes": [
					[
						96272.7272727273,
						2,
						0
					],
					[
						96681.8181818182,
						0,
						136.363636363636
					],
					[
						97090.9090909091,
						3,
						136.363636363636
					],
					[
						97636.3636363636,
						3,
						0
					],
					[
						98045.4545454545,
						0,
						0
					],
					[
						97909.0909090909,
						3,
						136.363636363636
					]
				],
				"sectionBeats": 4,
				"altAnim": false,
				"gfSection": false,
				"bpm": 110,
				"changeBPM": false,
				"mustHitSection": true
			},
			{
				"typeOfSection": 0,
				"sectionNotes": [
					[
						98181.8181818182,
						1,
						0
					],
					[
						98454.5454545454,
						1,
						0
					],
					[
						98863.6363636364,
						3,
						409.090909090909
					],
					[
						100090.909090909,
						2,
						136.363636363636
					],
					[
						99818.1818181818,
						0,
						136.363636363637
					]
				],
				"sectionBeats": 4,
				"altAnim": false,
				"gfSection": false,
				"bpm": 110,
				"changeBPM": false,
				"mustHitSection": true
			},
			{
				"typeOfSection": 0,
				"sectionNotes": [
					[
						100636.363636364,
						3,
						272.727272727273
					],
					[
						101045.454545455,
						1,
						272.727272727273
					],
					[
						101454.545454545,
						3,
						409.090909090909
					],
					[
						102000,
						1,
						0
					],
					[
						102272.727272727,
						0,
						0
					]
				],
				"sectionBeats": 4,
				"altAnim": false,
				"gfSection": false,
				"bpm": 110,
				"changeBPM": false,
				"mustHitSection": true
			},
			{
				"typeOfSection": 0,
				"sectionNotes": [
					[
						102545.454545455,
						2,
						136.363636363637
					],
					[
						102954.545454545,
						2,
						136.363636363637
					],
					[
						103363.636363636,
						2,
						136.363636363636
					],
					[
						103636.363636364,
						0,
						0
					],
					[
						103909.090909091,
						0,
						136.363636363637
					],
					[
						104454.545454545,
						0,
						136.363636363636
					],
					[
						104181.818181818,
						3,
						409.090909090909
					]
				],
				"sectionBeats": 4,
				"altAnim": false,
				"gfSection": false,
				"bpm": 110,
				"changeBPM": false,
				"mustHitSection": true
			},
			{
				"typeOfSection": 0,
				"sectionNotes": [
					[
						105000,
						1,
						0
					],
					[
						104727.272727273,
						1,
						136.363636363636
					],
					[
						105409.090909091,
						2,
						0
					],
					[
						105681.818181818,
						0,
						136.363636363636
					],
					[
						105818.181818182,
						3,
						409.090909090909
					],
					[
						106227.272727273,
						2,
						409.090909090909
					],
					[
						106636.363636364,
						3,
						0
					]
				],
				"sectionBeats": 4,
				"altAnim": false,
				"gfSection": false,
				"bpm": 110,
				"changeBPM": false,
				"mustHitSection": false
			},
			{
				"typeOfSection": 0,
				"sectionNotes": [
					[
						107181.818181818,
						2,
						272.727272727273
					],
					[
						107863.636363636,
						1,
						0
					],
					[
						107454.545454545,
						1,
						0
					],
					[
						107590.909090909,
						2,
						272.727272727273
					],
					[
						108000,
						0,
						272.727272727273
					],
					[
						108272.727272727,
						3,
						0
					],
					[
						108409.090909091,
						1,
						0
					],
					[
						108681.818181818,
						0,
						0
					],
					[
						108818.181818182,
						3,
						0
					]
				],
				"sectionBeats": 4,
				"altAnim": false,
				"gfSection": false,
				"bpm": 110,
				"changeBPM": false,
				"mustHitSection": false
			},
			{
				"typeOfSection": 0,
				"sectionNotes": [
					[
						109363.636363636,
						1,
						272.727272727273
					],
					[
						109636.363636364,
						0,
						0
					],
					[
						109772.727272727,
						1,
						272.727272727273
					],
					[
						110045.454545455,
						0,
						0
					],
					[
						110181.818181818,
						2,
						272.727272727273
					],
					[
						110454.545454545,
						3,
						0
					],
					[
						110590.909090909,
						1,
						0
					],
					[
						110863.636363636,
						0,
						0
					],
					[
						111000,
						3,
						0
					]
				],
				"sectionBeats": 4,
				"altAnim": false,
				"gfSection": false,
				"bpm": 110,
				"changeBPM": false,
				"mustHitSection": false
			},
			{
				"typeOfSection": 0,
				"sectionNotes": [
					[
						111545.454545455,
						0,
						0
					],
					[
						111681.818181818,
						3,
						0
					],
					[
						111818.181818182,
						2,
						0
					],
					[
						111954.545454545,
						0,
						272.727272727273
					],
					[
						112363.636363636,
						2,
						0
					],
					[
						112227.272727273,
						3,
						136.363636363636
					],
					[
						112636.363636364,
						0,
						0
					],
					[
						112772.727272727,
						1,
						409.090909090909
					],
					[
						113045.454545455,
						0,
						0
					],
					[
						113181.818181818,
						1,
						0
					]
				],
				"sectionBeats": 4,
				"altAnim": false,
				"gfSection": false,
				"bpm": 110,
				"changeBPM": false,
				"mustHitSection": false
			},
			{
				"typeOfSection": 0,
				"sectionNotes": [
					[
						113454.545454545,
						5,
						136.363636363636
					],
					[
						113454.545454545,
						1,
						136.363636363636
					],
					[
						114136.363636364,
						2,
						0
					],
					[
						114409.090909091,
						0,
						136.363636363636
					],
					[
						114545.454545455,
						3,
						272.727272727273
					],
					[
						114954.545454545,
						2,
						409.090909090909
					]
				],
				"sectionBeats": 4,
				"altAnim": false,
				"gfSection": false,
				"bpm": 110,
				"changeBPM": false,
				"mustHitSection": true
			},
			{
				"typeOfSection": 0,
				"sectionNotes": [
					[
						115909.090909091,
						2,
						136.363636363637
					],
					[
						116590.909090909,
						1,
						0
					],
					[
						116181.818181818,
						1,
						0
					],
					[
						116318.181818182,
						2,
						136.363636363637
					],
					[
						116727.272727273,
						0,
						272.727272727273
					],
					[
						117136.363636364,
						1,
						0
					],
					[
						117409.090909091,
						0,
						0
					],
					[
						117545.454545455,
						3,
						0
					]
				],
				"sectionBeats": 4,
				"altAnim": false,
				"gfSection": false,
				"bpm": 110,
				"changeBPM": false,
				"mustHitSection": true
			},
			{
				"typeOfSection": 0,
				"sectionNotes": [
					[
						118090.909090909,
						1,
						136.363636363637
					],
					[
						118500,
						1,
						136.363636363637
					],
					[
						118909.090909091,
						2,
						272.727272727273
					],
					[
						119318.181818182,
						1,
						0
					],
					[
						119590.909090909,
						0,
						0
					],
					[
						119727.272727273,
						3,
						0
					]
				],
				"sectionBeats": 4,
				"altAnim": false,
				"gfSection": false,
				"bpm": 110,
				"changeBPM": false,
				"mustHitSection": true
			},
			{
				"typeOfSection": 0,
				"sectionNotes": [
					[
						120272.727272727,
						0,
						0
					],
					[
						120409.090909091,
						3,
						0
					],
					[
						120545.454545455,
						2,
						0
					],
					[
						120681.818181818,
						0,
						272.727272727273
					],
					[
						121090.909090909,
						2,
						0
					],
					[
						120954.545454545,
						3,
						136.363636363636
					],
					[
						121363.636363636,
						0,
						0
					],
					[
						121500,
						1,
						409.090909090909
					],
					[
						120000,
						4,
						954.545454545454
					],
					[
						121090.909090909,
						5,
						954.545454545455
					]
				],
				"sectionBeats": 4,
				"altAnim": false,
				"gfSection": false,
				"bpm": 110,
				"changeBPM": false,
				"mustHitSection": true
			},
			{
				"typeOfSection": 0,
				"sectionNotes": [
					[
						122181.818181818,
						1,
						0
					],
					[
						122590.909090909,
						1,
						0
					],
					[
						122454.545454545,
						1,
						0
					],
					[
						122727.272727273,
						1,
						272.727272727273
					],
					[
						123000,
						3,
						272.727272727273
					],
					[
						123272.727272727,
						2,
						272.727272727273
					],
					[
						123545.454545455,
						3,
						272.727272727273
					],
					[
						123818.181818182,
						1,
						136.363636363636
					],
					[
						124090.909090909,
						0,
						136.363636363636
					],
					[
						123954.545454545,
						3,
						0
					]
				],
				"sectionBeats": 4,
				"altAnim": false,
				"gfSection": false,
				"bpm": 110,
				"changeBPM": false,
				"mustHitSection": false
			},
			{
				"typeOfSection": 0,
				"sectionNotes": [
					[
						124363.636363636,
						3,
						272.727272727273
					],
					[
						124636.363636364,
						1,
						0
					],
					[
						124909.090909091,
						3,
						272.727272727273
					],
					[
						125181.818181818,
						0,
						0
					],
					[
						125454.545454545,
						2,
						272.727272727273
					],
					[
						125727.272727273,
						3,
						0
					],
					[
						126000,
						0,
						0
					],
					[
						126272.727272727,
						1,
						0
					]
				],
				"sectionBeats": 4,
				"altAnim": false,
				"gfSection": false,
				"bpm": 110,
				"changeBPM": false,
				"mustHitSection": false
			},
			{
				"typeOfSection": 0,
				"sectionNotes": [
					[
						127363.636363636,
						3,
						272.727272727273
					],
					[
						127909.090909091,
						3,
						136.363636363637
					],
					[
						128181.818181818,
						1,
						2.8421709430404e-13
					],
					[
						128454.545454545,
						0,
						136.363636363636
					],
					[
						126545.454545455,
						0,
						272.727272727273
					],
					[
						127090.909090909,
						0,
						272.727272727273
					],
					[
						127363.636363636,
						7,
						272.727272727273
					],
					[
						127636.363636364,
						6,
						272.727272727273
					],
					[
						127909.090909091,
						7,
						272.727272727273
					],
					[
						128181.818181818,
						5,
						272.727272727273
					],
					[
						128454.545454545,
						4,
						136.363636363636
					],
					[
						126545.454545455,
						4,
						272.727272727273
					],
					[
						126818.181818182,
						5,
						0
					],
					[
						127090.909090909,
						4,
						272.727272727273
					],
					[
						127772.727272727,
						2,
						0
					]
				],
				"sectionBeats": 4,
				"altAnim": false,
				"gfSection": false,
				"bpm": 110,
				"changeBPM": false,
				"mustHitSection": true
			},
			{
				"typeOfSection": 0,
				"sectionNotes": [
					[
						128727.272727273,
						3,
						272.727272727273
					],
					[
						129272.727272727,
						3,
						272.727272727273
					],
					[
						129545.454545455,
						0,
						0
					],
					[
						129818.181818182,
						2,
						136.363636363637
					],
					[
						130090.909090909,
						3,
						136.363636363637
					],
					[
						130363.636363636,
						0,
						0
					],
					[
						129136.363636364,
						1,
						0
					],
					[
						130636.363636364,
						3,
						272.727272727273
					],
					[
						128727.272727273,
						7,
						272.727272727273
					],
					[
						129272.727272727,
						7,
						272.727272727273
					],
					[
						129545.454545455,
						4,
						0
					],
					[
						129818.181818182,
						6,
						272.727272727273
					],
					[
						130090.909090909,
						7,
						272.727272727273
					],
					[
						130363.636363636,
						4,
						0
					],
					[
						129136.363636364,
						5,
						0
					],
					[
						130636.363636364,
						7,
						272.727272727273
					]
				],
				"sectionBeats": 4,
				"altAnim": false,
				"gfSection": false,
				"bpm": 110,
				"changeBPM": false,
				"mustHitSection": true
			},
			{
				"typeOfSection": 0,
				"sectionNotes": [
					[
						130909.090909091,
						6,
						0
					]
				],
				"sectionBeats": 4,
				"altAnim": false,
				"gfSection": false,
				"bpm": 110,
				"changeBPM": false,
				"mustHitSection": true
			},
			{
				"typeOfSection": 0,
				"sectionNotes": [],
				"sectionBeats": 4,
				"altAnim": false,
				"gfSection": false,
				"bpm": 110,
				"changeBPM": false,
				"mustHitSection": true
			},
			{
				"typeOfSection": 0,
				"sectionNotes": [],
				"sectionBeats": 4,
				"altAnim": false,
				"gfSection": false,
				"bpm": 110,
				"changeBPM": false,
				"mustHitSection": true
			},
			{
				"typeOfSection": 0,
				"sectionNotes": [],
				"sectionBeats": 4,
				"altAnim": false,
				"gfSection": false,
				"bpm": 110,
				"changeBPM": false,
				"mustHitSection": true
			},
			{
				"typeOfSection": 0,
				"sectionNotes": [],
				"sectionBeats": 4,
				"altAnim": false,
				"gfSection": false,
				"bpm": 110,
				"changeBPM": false,
				"mustHitSection": true
			},
			{
				"sectionBeats": 4,
				"sectionNotes": [],
				"typeOfSection": 0,
				"gfSection": false,
				"altAnim": false,
				"mustHitSection": true,
				"changeBPM": false,
				"bpm": 110
			},
			{
				"gfSection": false,
				"altAnim": false,
				"typeOfSection": 0,
				"sectionNotes": [],
				"bpm": 110,
				"sectionBeats": 4,
				"changeBPM": false,
				"mustHitSection": true
			},
			{
				"gfSection": false,
				"altAnim": false,
				"typeOfSection": 0,
				"sectionNotes": [],
				"bpm": 110,
				"sectionBeats": 4,
				"changeBPM": false,
				"mustHitSection": true
			}
		],
		"gfVersion": "gf-flora",
		"splashSkin": "noteSplashes",
		"song": "warmup",
		"validScore": true,
		"stage": "weekbonnieStage",
		"arrowSkin": "",
		"needsVoices": true,
		"speed": 2,
		"bpm": 110
	}
}