{
	"animations": [
		{
			"offsets": [
				0,
				1
			],
			"loop": false,
			"fps": 24,
			"anim": "idle",
			"indices": [],
			"name": "bonnie_idle"
		},
		{
			"offsets": [
				0,
				3
			],
			"loop": false,
			"fps": 24,
			"anim": "singDOWN",
			"indices": [],
			"name": "bonnie_down"
		},
		{
			"offsets": [
				-3,
				-3
			],
			"loop": false,
			"fps": 24,
			"anim": "singUP",
			"indices": [],
			"name": "bonnie_up"
		},
		{
			"loop": false,
			"offsets": [
				-18,
				33
			],
			"anim": "singRIGHT",
			"fps": 24,
			"name": "bonnie_right",
			"indices": []
		},
		{
			"loop": false,
			"offsets": [
				3,
				-1
			],
			"anim": "singLEFT",
			"fps": 24,
			"name": "bonnie_left",
			"indices": []
		}
	],
	"no_antialiasing": false,
	"image": "characters/bonnie",
	"position": [
		-30,
		170
	],
	"healthicon": "bonnierad",
	"flip_x": false,
	"healthbar_colors": [
		160,
		135,
		255
	],
	"camera_position": [
		0,
		0
	],
	"sing_duration": 4,
	"scale": 1
}